LICENSE
README.md
pyproject.toml
setup.cfg
src/toqan/__init__.py
src/toqan/engine.py
src/toqan.egg-info/PKG-INFO
src/toqan.egg-info/SOURCES.txt
src/toqan.egg-info/dependency_links.txt
src/toqan.egg-info/top_level.txt