Metadata-Version: 2.4
Name: toqan
Version: 0.0.1
Summary: toqan package
Author-email: CK <author@example.com>
License-Expression: MIT
Classifier: Programming Language :: Python :: 3
Classifier: Operating System :: OS Independent
Requires-Python: >=4.0
License-File: LICENSE
Dynamic: license-file
